k8scmd/__init__.py
k8scmd/cmd.py
k8scmd/util.py
k8scmd-1.0.1.dist-info/METADATA
k8scmd-1.0.1.dist-info/WHEEL
k8scmd-1.0.1.dist-info/entry_points.txt
k8scmd-1.0.1.dist-info/top_level.txt
k8scmd-1.0.1.dist-info/RECORD
