Metadata-Version: 2.1
Name: k8scmd
Version: 1.0.1
Summary: k8scmd: easy way to execute k8s command
Home-page: https://github.com/shigebeyond/k8scmd
Author: shigebeyond
Author-email: 772910474@qq.com
License: BSD
Classifier: Development Status :: 5 - Production/Stable
Classifier: Topic :: Software Development :: Libraries :: Python Modules
Classifier: Operating System :: POSIX :: Linux
Classifier: Operating System :: MacOS :: MacOS X
Classifier: Operating System :: Microsoft :: Windows
Classifier: Programming Language :: Python
Classifier: Programming Language :: Python :: 3.7
Classifier: Programming Language :: Python :: 3.8
Classifier: Programming Language :: Python :: 3.9
Requires-Python: >=3.6
Requires-Dist: pyutilb (>=1.0.7)
